iblqt/__init__.py
iblqt/core.py
iblqt/py.typed
iblqt/resources.py
iblqt/tools.py
iblqt/widgets.py
iblqt-0.8.2.dist-info/WHEEL
iblqt-0.8.2.dist-info/METADATA
iblqt-0.8.2.dist-info/RECORD
